engine/__init__.py
engine/agent.py
tools/__init__.py
tools/calculator.py
tools/python_repl.py
tools/schema.py
june_llm_agent-0.0.1.dist-info/LICENSE
june_llm_agent-0.0.1.dist-info/METADATA
june_llm_agent-0.0.1.dist-info/WHEEL
june_llm_agent-0.0.1.dist-info/top_level.txt
june_llm_agent-0.0.1.dist-info/RECORD
